shichengtools/__init__.py
shichengtools/common_used_tools.py
shichengtools-0.0.7.dist-info/METADATA
shichengtools-0.0.7.dist-info/RECORD
shichengtools-0.0.7.dist-info/WHEEL
shichengtools-0.0.7.dist-info/top_level.txt
